QtWekaWrapper/__init__.py
QtWekaWrapper/data.py
QtWekaWrapper/main.py
QtWekaWrapper/qtwekawrapper.py
QtWekaWrapper/tests.py
QtWekaWrapper/fixtures/abalone-train.arff
QtWekaWrapper/fixtures/fake-abalone-test.arff
QtWekaWrapper/vis/StarPlot.py
QtWekaWrapper/vis/VisWidget.py
QtWekaWrapper/vis/__init__.py
QtWekaWrapper-0.0.3.dist-info/LICENSE
QtWekaWrapper-0.0.3.dist-info/METADATA
QtWekaWrapper-0.0.3.dist-info/WHEEL
QtWekaWrapper-0.0.3.dist-info/top_level.txt
QtWekaWrapper-0.0.3.dist-info/RECORD
