Metadata-Version: 2.1
Name: QtWekaWrapper
Version: 0.0.3
Summary: A Python wrapper for the Weka graphics .
Home-page: https://github.com/Nicusor97/WekaPythonWrapper
Author: Picatureanu Nicusor
Author-email: nicolaepicatureanu@gmail.com
License: MIT License
Platform: OS Independent
Classifier: Programming Language :: Python :: 3.5
Classifier: Programming Language :: Python :: 3.6
Classifier: Operating System :: OS Independent
Classifier: Topic :: Software Development :: Libraries :: Python Modules
Classifier: Topic :: Text Processing :: General
Requires-Dist: PyQt5
Requires-Dist: six (>=1.11.0)
Requires-Dist: python-dateutil (>=2.6.1)
Requires-Dist: pytest
Requires-Dist: Sphinx (==1.4.2)
